{
  "tag": "2021-12-06_205209",
  "state_str": "7d3d19f3860b7730d71aff15acabdec1",
  "state_str_content_free": "e4dea1940ae53c27f779ddd95d4d3144",
  "foreground_activity": "org.chromium.webview_shell/.WebViewBrowserActivity",
  "activity_stack": [
    "org.chromium.webview_shell/.WebViewBrowserActivity"
  ],
  "background_services": [
    "com.android.dialer/com.android.voicemail.impl.scheduling.TaskSchedulerJobService",
    "com.android.providers.media.module/com.android.providers.media.fuse.ExternalStorageServiceImpl",
    "android.ext.services/.notification.Assistant",
    "com.google.android.gms/.deviceconnection.service.DeviceConnectionWatcherService",
    "com.android.systemui/.keyguard.KeyguardService",
    "com.android.bluetooth/.btservice.AdapterService",
    "com.android.systemui/.ImageWallpaper",
    "com.google.android.gms/com.google.android.location.geocode.GeocodeService",
    "org.chromium.webview_shell/org.chromium.content.app.SandboxedProcessService0",
    "com.google.android.gms/.auth.setup.devicesignals.LockScreenService",
    "com.google.android.gms/.gcm.GcmService",
    "com.google.android.gms/.clearcut.debug.ClearcutDebugDumpService",
    "com.android.phone/com.android.internal.telephony.CellularNetworkService",
    "com.google.android.gms/com.google.location.nearby.direct.service.NearbyDirectService",
    "com.google.android.gms/.chimera.PersistentBoundBrokerService",
    "com.android.bluetooth/.gatt.GattService",
    "com.google.android.gms/.fido.fido2.pollux.CableAuthenticatorService",
    "io.github.ylimit.droidbotapp/.DroidBotIME",
    "com.android.bluetooth/.pbap.BluetoothPbapService",
    "com.google.android.gms/.beacon.BleService",
    "com.google.android.gms/com.google.android.location.fused.FusedLocationService",
    "com.android.networkstack/com.android.server.NetworkStackService",
    "com.google.android.gms/.gcm.nts.SchedulerService",
    "com.android.bluetooth/.a2dp.A2dpService",
    "com.android.cellbroadcastservice/.DefaultCellBroadcastService",
    "io.github.ylimit.droidbotapp/io.github.privacystreams.accessibility.PSAccessibilityService",
    "com.google.android.gms/com.google.android.location.geofencer.service.GeofenceProviderService",
    "com.google.android.gms/.thunderbird.EmergencyPersistentService",
    "com.android.systemui/.SystemUIService",
    "android/.hardware.location.GeofenceHardwareService",
    "com.android.se/.SecureElementService",
    "com.google.android.gms/.chimera.GmsIntentOperationService",
    "com.google.android.gms/.chimera.PersistentDirectBootAwareApiService",
    "com.google.android.gms/.chimera.PersistentIntentOperationService",
    "com.android.bluetooth/.hid.HidDeviceService",
    "com.google.android.gms/.location.persistent.LocationPersistentService",
    "com.google.android.gms/.nearby.discovery.service.DiscoveryService",
    "com.google.android.gms/com.google.android.location.internal.PendingIntentCallbackService",
    "com.google.android.gms/.nearby.messages.service.NearbyMessagesService",
    "com.android.server.telecom/.components.BluetoothPhoneService",
    "com.google.android.gms/com.google.android.location.internal.server.GoogleLocationService",
    "com.android.systemui/.dump.SystemUIAuxiliaryDumpService",
    "com.google.android.gms/com.google.android.location.network.NetworkLocationService",
    "com.android.stk/.StkAppService",
    "com.google.android.gms/com.google.android.location.internal.GoogleLocationManagerService",
    "com.android.networkstack.tethering/.TetheringService",
    "com.android.phone/com.android.internal.telephony.dataconnection.CellularDataService",
    "com.android.service.ims/.RcsService",
    "com.android.server.telecom/.components.TelecomService",
    "com.android.launcher3/com.android.quickstep.TouchInteractionService",
    "com.android.bluetooth/.hfp.HeadsetService",
    "com.android.emulator.multidisplay/.MultiDisplayService",
    "com.android.phone/.vvm.RemoteVvmTaskManager",
    "com.android.ons/.OpportunisticNetworkService",
    "com.google.android.gms/.common.stats.GmsCoreStatsService",
    "com.google.android.gms/com.google.android.location.internal.server.HardwareArProviderService",
    "com.android.bluetooth/.map.BluetoothMapService",
    "com.android.phone/com.android.services.telephony.sip.components.TelephonySipService",
    "com.android.phone/.TelephonyDebugService",
    "com.android.bluetooth/.hid.HidHostService",
    "com.android.bluetooth/.opp.BluetoothOppService",
    "com.android.bluetooth/.pan.PanService",
    "com.android.bluetooth/.avrcp.AvrcpTargetService",
    "android.ext.services/.autofill.InlineSuggestionRenderServiceImpl"
  ],
  "width": 1080,
  "height": 2280,
  "views": [
    {
      "package": "org.chromium.webview_shell",
      "visible": true,
      "checkable": false,
      "child_count": 1,
      "editable": false,
      "clickable": false,
      "is_password": false,
      "focusable": false,
      "enabled": true,
      "content_description": null,
      "children": [
        1
      ],
      "focused": false,
      "bounds": [
        [
          178,
          345
        ],
        [
          1080,
          1440
        ]
      ],
      "resource_id": null,
      "checked": false,
      "text": null,
      "class": "android.widget.FrameLayout",
      "scrollable": false,
      "selected": false,
      "long_clickable": false,
      "parent": -1,
      "temp_id": 0,
      "size": "902*1095",
      "signature": "[class]android.widget.FrameLayout[resource_id]None[text]None[enabled,,]",
      "view_str": "846d65c294cfb2cc1e28dd9a3a6a11f5"
    },
    {
      "package": "org.chromium.webview_shell",
      "visible": true,
      "checkable": false,
      "child_count": 1,
      "editable": false,
      "clickable": false,
      "is_password": false,
      "focusable": false,
      "enabled": true,
      "content_description": null,
      "children": [
        2
      ],
      "focused": false,
      "bounds": [
        [
          178,
          345
        ],
        [
          1080,
          1440
        ]
      ],
      "resource_id": null,
      "checked": false,
      "text": null,
      "class": "android.widget.FrameLayout",
      "scrollable": false,
      "selected": false,
      "long_clickable": false,
      "parent": 0,
      "temp_id": 1,
      "size": "902*1095",
      "signature": "[class]android.widget.FrameLayout[resource_id]None[text]None[enabled,,]",
      "view_str": "4e97275fe532a32786daaa5ed8e5ffe7"
    },
    {
      "package": "org.chromium.webview_shell",
      "visible": true,
      "checkable": false,
      "child_count": 6,
      "editable": false,
      "clickable": false,
      "is_password": false,
      "focusable": true,
      "enabled": true,
      "content_description": null,
      "children": [
        3,
        7,
        11,
        16,
        20,
        24
      ],
      "focused": true,
      "bounds": [
        [
          189,
          362
        ],
        [
          1069,
          1423
        ]
      ],
      "resource_id": null,
      "checked": false,
      "text": null,
      "class": "android.widget.ListView",
      "scrollable": false,
      "selected": false,
      "long_clickable": false,
      "parent": 1,
      "temp_id": 2,
      "size": "880*1061",
      "signature": "[class]android.widget.ListView[resource_id]None[text]None[enabled,,]",
      "view_str": "8041ce6a6b0216e8cdf3ccd9262d7593"
    },
    {
      "package": "org.chromium.webview_shell",
      "visible": true,
      "checkable": false,
      "child_count": 1,
      "editable": false,
      "clickable": true,
      "is_password": false,
      "focusable": false,
      "enabled": true,
      "content_description": null,
      "children": [
        4
      ],
      "focused": false,
      "bounds": [
        [
          189,
          362
        ],
        [
          1069,
          538
        ]
      ],
      "resource_id": null,
      "checked": false,
      "text": null,
      "class": "android.widget.LinearLayout",
      "scrollable": false,
      "selected": false,
      "long_clickable": false,
      "parent": 2,
      "temp_id": 3,
      "size": "880*176",
      "signature": "[class]android.widget.LinearLayout[resource_id]None[text]None[enabled,,]",
      "view_str": "b0f1db155a9416e24d528abde17d051d"
    },
    {
      "package": "org.chromium.webview_shell",
      "visible": true,
      "checkable": false,
      "child_count": 1,
      "editable": false,
      "clickable": false,
      "is_password": false,
      "focusable": false,
      "enabled": true,
      "content_description": null,
      "children": [
        5
      ],
      "focused": false,
      "bounds": [
        [
          189,
          362
        ],
        [
          1069,
          538
        ]
      ],
      "resource_id": "android:id/content",
      "checked": false,
      "text": null,
      "class": "android.widget.LinearLayout",
      "scrollable": false,
      "selected": false,
      "long_clickable": false,
      "parent": 3,
      "temp_id": 4,
      "size": "880*176",
      "signature": "[class]android.widget.LinearLayout[resource_id]android:id/content[text]None[enabled,,]",
      "view_str": "39e154231ae3fd741b892bbea0be606f"
    },
    {
      "package": "org.chromium.webview_shell",
      "visible": true,
      "checkable": false,
      "child_count": 1,
      "editable": false,
      "clickable": false,
      "is_password": false,
      "focusable": false,
      "enabled": true,
      "content_description": null,
      "children": [
        6
      ],
      "focused": false,
      "bounds": [
        [
          233,
          409
        ],
        [
          1025,
          491
        ]
      ],
      "resource_id": null,
      "checked": false,
      "text": null,
      "class": "android.widget.RelativeLayout",
      "scrollable": false,
      "selected": false,
      "long_clickable": false,
      "parent": 4,
      "temp_id": 5,
      "size": "792*82",
      "signature": "[class]android.widget.RelativeLayout[resource_id]None[text]None[enabled,,]",
      "view_str": "4494d425cc3defd6c66956372e4cdfd6"
    },
    {
      "package": "org.chromium.webview_shell",
      "visible": true,
      "checkable": false,
      "child_count": 0,
      "editable": false,
      "clickable": false,
      "is_password": false,
      "focusable": false,
      "enabled": true,
      "content_description": null,
      "children": [],
      "focused": false,
      "bounds": [
        [
          233,
          409
        ],
        [
          1025,
          491
        ]
      ],
      "resource_id": "android:id/title",
      "checked": false,
      "text": "Destroy and create new WebView",
      "class": "android.widget.TextView",
      "scrollable": false,
      "selected": false,
      "long_clickable": false,
      "parent": 5,
      "temp_id": 6,
      "size": "792*82",
      "signature": "[class]android.widget.TextView[resource_id]android:id/title[text]Destroy and create new WebView[enabled,,]",
      "view_str": "19d5c3f780f4c4d1eb5c6b6e02f032f2"
    },
    {
      "package": "org.chromium.webview_shell",
      "visible": true,
      "checkable": false,
      "child_count": 1,
      "editable": false,
      "clickable": true,
      "is_password": false,
      "focusable": false,
      "enabled": true,
      "content_description": null,
      "children": [
        8
      ],
      "focused": false,
      "bounds": [
        [
          189,
          539
        ],
        [
          1069,
          715
        ]
      ],
      "resource_id": null,
      "checked": false,
      "text": null,
      "class": "android.widget.LinearLayout",
      "scrollable": false,
      "selected": false,
      "long_clickable": false,
      "parent": 2,
      "temp_id": 7,
      "size": "880*176",
      "signature": "[class]android.widget.LinearLayout[resource_id]None[text]None[enabled,,]",
      "view_str": "b0f1db155a9416e24d528abde17d051d"
    },
    {
      "package": "org.chromium.webview_shell",
      "visible": true,
      "checkable": false,
      "child_count": 1,
      "editable": false,
      "clickable": false,
      "is_password": false,
      "focusable": false,
      "enabled": true,
      "content_description": null,
      "children": [
        9
      ],
      "focused": false,
      "bounds": [
        [
          189,
          539
        ],
        [
          1069,
          715
        ]
      ],
      "resource_id": "android:id/content",
      "checked": false,
      "text": null,
      "class": "android.widget.LinearLayout",
      "scrollable": false,
      "selected": false,
      "long_clickable": false,
      "parent": 7,
      "temp_id": 8,
      "size": "880*176",
      "signature": "[class]android.widget.LinearLayout[resource_id]android:id/content[text]None[enabled,,]",
      "view_str": "39e154231ae3fd741b892bbea0be606f"
    },
    {
      "package": "org.chromium.webview_shell",
      "visible": true,
      "checkable": false,
      "child_count": 1,
      "editable": false,
      "clickable": false,
      "is_password": false,
      "focusable": false,
      "enabled": true,
      "content_description": null,
      "children": [
        10
      ],
      "focused": false,
      "bounds": [
        [
          233,
          586
        ],
        [
          1025,
          668
        ]
      ],
      "resource_id": null,
      "checked": false,
      "text": null,
      "class": "android.widget.RelativeLayout",
      "scrollable": false,
      "selected": false,
      "long_clickable": false,
      "parent": 8,
      "temp_id": 9,
      "size": "792*82",
      "signature": "[class]android.widget.RelativeLayout[resource_id]None[text]None[enabled,,]",
      "view_str": "334c3ed38ef6d9bf8822938906f49e13"
    },
    {
      "package": "org.chromium.webview_shell",
      "visible": true,
      "checkable": false,
      "child_count": 0,
      "editable": false,
      "clickable": false,
      "is_password": false,
      "focusable": false,
      "enabled": true,
      "content_description": null,
      "children": [],
      "focused": false,
      "bounds": [
        [
          233,
          586
        ],
        [
          1025,
          668
        ]
      ],
      "resource_id": "android:id/title",
      "checked": false,
      "text": "Clear cache",
      "class": "android.widget.TextView",
      "scrollable": false,
      "selected": false,
      "long_clickable": false,
      "parent": 9,
      "temp_id": 10,
      "size": "792*82",
      "signature": "[class]android.widget.TextView[resource_id]android:id/title[text]Clear cache[enabled,,]",
      "view_str": "43a7e8908cdddb02fb4225bb431ec84a"
    },
    {
      "package": "org.chromium.webview_shell",
      "visible": true,
      "checkable": false,
      "child_count": 1,
      "editable": false,
      "clickable": true,
      "is_password": false,
      "focusable": false,
      "enabled": true,
      "content_description": null,
      "children": [
        12
      ],
      "focused": false,
      "bounds": [
        [
          189,
          716
        ],
        [
          1069,
          892
        ]
      ],
      "resource_id": null,
      "checked": false,
      "text": null,
      "class": "android.widget.LinearLayout",
      "scrollable": false,
      "selected": false,
      "long_clickable": false,
      "parent": 2,
      "temp_id": 11,
      "size": "880*176",
      "signature": "[class]android.widget.LinearLayout[resource_id]None[text]None[enabled,,]",
      "view_str": "b0f1db155a9416e24d528abde17d051d"
    },
    {
      "package": "org.chromium.webview_shell",
      "visible": true,
      "checkable": false,
      "child_count": 2,
      "editable": false,
      "clickable": false,
      "is_password": false,
      "focusable": false,
      "enabled": true,
      "content_description": null,
      "children": [
        13,
        15
      ],
      "focused": false,
      "bounds": [
        [
          189,
          716
        ],
        [
          1069,
          892
        ]
      ],
      "resource_id": "android:id/content",
      "checked": false,
      "text": null,
      "class": "android.widget.LinearLayout",
      "scrollable": false,
      "selected": false,
      "long_clickable": false,
      "parent": 11,
      "temp_id": 12,
      "size": "880*176",
      "signature": "[class]android.widget.LinearLayout[resource_id]android:id/content[text]None[enabled,,]",
      "view_str": "1f14620e167ab186188926026c27fc5a"
    },
    {
      "package": "org.chromium.webview_shell",
      "visible": true,
      "checkable": false,
      "child_count": 1,
      "editable": false,
      "clickable": false,
      "is_password": false,
      "focusable": false,
      "enabled": true,
      "content_description": null,
      "children": [
        14
      ],
      "focused": false,
      "bounds": [
        [
          233,
          763
        ],
        [
          920,
          845
        ]
      ],
      "resource_id": null,
      "checked": false,
      "text": null,
      "class": "android.widget.RelativeLayout",
      "scrollable": false,
      "selected": false,
      "long_clickable": false,
      "parent": 12,
      "temp_id": 13,
      "size": "687*82",
      "signature": "[class]android.widget.RelativeLayout[resource_id]None[text]None[enabled,,]",
      "view_str": "4637845b59d73d38d75c1c416461fdc4"
    },
    {
      "package": "org.chromium.webview_shell",
      "visible": true,
      "checkable": false,
      "child_count": 0,
      "editable": false,
      "clickable": false,
      "is_password": false,
      "focusable": false,
      "enabled": true,
      "content_description": null,
      "children": [],
      "focused": false,
      "bounds": [
        [
          233,
          763
        ],
        [
          920,
          845
        ]
      ],
      "resource_id": "android:id/title",
      "checked": false,
      "text": "Enable tracing",
      "class": "android.widget.TextView",
      "scrollable": false,
      "selected": false,
      "long_clickable": false,
      "parent": 13,
      "temp_id": 14,
      "size": "687*82",
      "signature": "[class]android.widget.TextView[resource_id]android:id/title[text]Enable tracing[enabled,,]",
      "view_str": "05390ab34cfb15e12b1ea0bc3ff3801b"
    },
    {
      "package": "org.chromium.webview_shell",
      "visible": true,
      "checkable": true,
      "child_count": 0,
      "editable": false,
      "clickable": false,
      "is_password": false,
      "focusable": false,
      "enabled": true,
      "content_description": null,
      "children": [],
      "focused": false,
      "bounds": [
        [
          920,
          738
        ],
        [
          1025,
          870
        ]
      ],
      "resource_id": "android:id/checkbox",
      "checked": false,
      "text": null,
      "class": "android.widget.CheckBox",
      "scrollable": false,
      "selected": false,
      "long_clickable": false,
      "parent": 12,
      "temp_id": 15,
      "size": "105*132",
      "signature": "[class]android.widget.CheckBox[resource_id]android:id/checkbox[text]None[enabled,,]",
      "view_str": "a7c7dea2ab5a6b01051af90b891b7b36"
    },
    {
      "package": "org.chromium.webview_shell",
      "visible": true,
      "checkable": false,
      "child_count": 1,
      "editable": false,
      "clickable": true,
      "is_password": false,
      "focusable": false,
      "enabled": true,
      "content_description": null,
      "children": [
        17
      ],
      "focused": false,
      "bounds": [
        [
          189,
          893
        ],
        [
          1069,
          1069
        ]
      ],
      "resource_id": null,
      "checked": false,
      "text": null,
      "class": "android.widget.LinearLayout",
      "scrollable": false,
      "selected": false,
      "long_clickable": false,
      "parent": 2,
      "temp_id": 16,
      "size": "880*176",
      "signature": "[class]android.widget.LinearLayout[resource_id]None[text]None[enabled,,]",
      "view_str": "b0f1db155a9416e24d528abde17d051d"
    },
    {
      "package": "org.chromium.webview_shell",
      "visible": true,
      "checkable": false,
      "child_count": 1,
      "editable": false,
      "clickable": false,
      "is_password": false,
      "focusable": false,
      "enabled": true,
      "content_description": null,
      "children": [
        18
      ],
      "focused": false,
      "bounds": [
        [
          189,
          893
        ],
        [
          1069,
          1069
        ]
      ],
      "resource_id": "android:id/content",
      "checked": false,
      "text": null,
      "class": "android.widget.LinearLayout",
      "scrollable": false,
      "selected": false,
      "long_clickable": false,
      "parent": 16,
      "temp_id": 17,
      "size": "880*176",
      "signature": "[class]android.widget.LinearLayout[resource_id]android:id/content[text]None[enabled,,]",
      "view_str": "39e154231ae3fd741b892bbea0be606f"
    },
    {
      "package": "org.chromium.webview_shell",
      "visible": true,
      "checkable": false,
      "child_count": 1,
      "editable": false,
      "clickable": false,
      "is_password": false,
      "focusable": false,
      "enabled": true,
      "content_description": null,
      "children": [
        19
      ],
      "focused": false,
      "bounds": [
        [
          233,
          940
        ],
        [
          1025,
          1022
        ]
      ],
      "resource_id": null,
      "checked": false,
      "text": null,
      "class": "android.widget.RelativeLayout",
      "scrollable": false,
      "selected": false,
      "long_clickable": false,
      "parent": 17,
      "temp_id": 18,
      "size": "792*82",
      "signature": "[class]android.widget.RelativeLayout[resource_id]None[text]None[enabled,,]",
      "view_str": "b782ff97a0f958b8143c06c7be214996"
    },
    {
      "package": "org.chromium.webview_shell",
      "visible": true,
      "checkable": false,
      "child_count": 0,
      "editable": false,
      "clickable": false,
      "is_password": false,
      "focusable": false,
      "enabled": true,
      "content_description": null,
      "children": [],
      "focused": false,
      "bounds": [
        [
          233,
          940
        ],
        [
          1025,
          1022
        ]
      ],
      "resource_id": "android:id/title",
      "checked": false,
      "text": "Print",
      "class": "android.widget.TextView",
      "scrollable": false,
      "selected": false,
      "long_clickable": false,
      "parent": 18,
      "temp_id": 19,
      "size": "792*82",
      "signature": "[class]android.widget.TextView[resource_id]android:id/title[text]Print[enabled,,]",
      "view_str": "e15302a55ebce3d3ebd7771d20dad561"
    },
    {
      "package": "org.chromium.webview_shell",
      "visible": true,
      "checkable": false,
      "child_count": 1,
      "editable": false,
      "clickable": true,
      "is_password": false,
      "focusable": false,
      "enabled": true,
      "content_description": null,
      "children": [
        21
      ],
      "focused": false,
      "bounds": [
        [
          189,
          1070
        ],
        [
          1069,
          1246
        ]
      ],
      "resource_id": null,
      "checked": false,
      "text": null,
      "class": "android.widget.LinearLayout",
      "scrollable": false,
      "selected": false,
      "long_clickable": false,
      "parent": 2,
      "temp_id": 20,
      "size": "880*176",
      "signature": "[class]android.widget.LinearLayout[resource_id]None[text]None[enabled,,]",
      "view_str": "b0f1db155a9416e24d528abde17d051d"
    },
    {
      "package": "org.chromium.webview_shell",
      "visible": true,
      "checkable": false,
      "child_count": 1,
      "editable": false,
      "clickable": false,
      "is_password": false,
      "focusable": false,
      "enabled": true,
      "content_description": null,
      "children": [
        22
      ],
      "focused": false,
      "bounds": [
        [
          189,
          1070
        ],
        [
          1069,
          1246
        ]
      ],
      "resource_id": "android:id/content",
      "checked": false,
      "text": null,
      "class": "android.widget.LinearLayout",
      "scrollable": false,
      "selected": false,
      "long_clickable": false,
      "parent": 20,
      "temp_id": 21,
      "size": "880*176",
      "signature": "[class]android.widget.LinearLayout[resource_id]android:id/content[text]None[enabled,,]",
      "view_str": "39e154231ae3fd741b892bbea0be606f"
    },
    {
      "package": "org.chromium.webview_shell",
      "visible": true,
      "checkable": false,
      "child_count": 1,
      "editable": false,
      "clickable": false,
      "is_password": false,
      "focusable": false,
      "enabled": true,
      "content_description": null,
      "children": [
        23
      ],
      "focused": false,
      "bounds": [
        [
          233,
          1117
        ],
        [
          1025,
          1199
        ]
      ],
      "resource_id": null,
      "checked": false,
      "text": null,
      "class": "android.widget.RelativeLayout",
      "scrollable": false,
      "selected": false,
      "long_clickable": false,
      "parent": 21,
      "temp_id": 22,
      "size": "792*82",
      "signature": "[class]android.widget.RelativeLayout[resource_id]None[text]None[enabled,,]",
      "view_str": "7f6585e03ff44ca93f3a912939864ebd"
    },
    {
      "package": "org.chromium.webview_shell",
      "visible": true,
      "checkable": false,
      "child_count": 0,
      "editable": false,
      "clickable": false,
      "is_password": false,
      "focusable": false,
      "enabled": true,
      "content_description": null,
      "children": [],
      "focused": false,
      "bounds": [
        [
          233,
          1117
        ],
        [
          1025,
          1199
        ]
      ],
      "resource_id": "android:id/title",
      "checked": false,
      "text": "Animation test",
      "class": "android.widget.TextView",
      "scrollable": false,
      "selected": false,
      "long_clickable": false,
      "parent": 22,
      "temp_id": 23,
      "size": "792*82",
      "signature": "[class]android.widget.TextView[resource_id]android:id/title[text]Animation test[enabled,,]",
      "view_str": "0f8d78b2e18e90b75989a6cbaec184c8"
    },
    {
      "package": "org.chromium.webview_shell",
      "visible": true,
      "checkable": false,
      "child_count": 1,
      "editable": false,
      "clickable": true,
      "is_password": false,
      "focusable": false,
      "enabled": true,
      "content_description": null,
      "children": [
        25
      ],
      "focused": false,
      "bounds": [
        [
          189,
          1247
        ],
        [
          1069,
          1423
        ]
      ],
      "resource_id": null,
      "checked": false,
      "text": null,
      "class": "android.widget.LinearLayout",
      "scrollable": false,
      "selected": false,
      "long_clickable": false,
      "parent": 2,
      "temp_id": 24,
      "size": "880*176",
      "signature": "[class]android.widget.LinearLayout[resource_id]None[text]None[enabled,,]",
      "view_str": "b0f1db155a9416e24d528abde17d051d"
    },
    {
      "package": "org.chromium.webview_shell",
      "visible": true,
      "checkable": false,
      "child_count": 1,
      "editable": false,
      "clickable": false,
      "is_password": false,
      "focusable": false,
      "enabled": true,
      "content_description": null,
      "children": [
        26
      ],
      "focused": false,
      "bounds": [
        [
          189,
          1247
        ],
        [
          1069,
          1423
        ]
      ],
      "resource_id": "android:id/content",
      "checked": false,
      "text": null,
      "class": "android.widget.LinearLayout",
      "scrollable": false,
      "selected": false,
      "long_clickable": false,
      "parent": 24,
      "temp_id": 25,
      "size": "880*176",
      "signature": "[class]android.widget.LinearLayout[resource_id]android:id/content[text]None[enabled,,]",
      "view_str": "39e154231ae3fd741b892bbea0be606f"
    },
    {
      "package": "org.chromium.webview_shell",
      "visible": true,
      "checkable": false,
      "child_count": 1,
      "editable": false,
      "clickable": false,
      "is_password": false,
      "focusable": false,
      "enabled": true,
      "content_description": null,
      "children": [
        27
      ],
      "focused": false,
      "bounds": [
        [
          233,
          1294
        ],
        [
          1025,
          1376
        ]
      ],
      "resource_id": null,
      "checked": false,
      "text": null,
      "class": "android.widget.RelativeLayout",
      "scrollable": false,
      "selected": false,
      "long_clickable": false,
      "parent": 25,
      "temp_id": 26,
      "size": "792*82",
      "signature": "[class]android.widget.RelativeLayout[resource_id]None[text]None[enabled,,]",
      "view_str": "420fdb9197a309d70c560e0cad96e6c3"
    },
    {
      "package": "org.chromium.webview_shell",
      "visible": true,
      "checkable": false,
      "child_count": 0,
      "editable": false,
      "clickable": false,
      "is_password": false,
      "focusable": false,
      "enabled": true,
      "content_description": null,
      "children": [],
      "focused": false,
      "bounds": [
        [
          233,
          1294
        ],
        [
          1025,
          1376
        ]
      ],
      "resource_id": "android:id/title",
      "checked": false,
      "text": "About WebView",
      "class": "android.widget.TextView",
      "scrollable": false,
      "selected": false,
      "long_clickable": false,
      "parent": 26,
      "temp_id": 27,
      "size": "792*82",
      "signature": "[class]android.widget.TextView[resource_id]android:id/title[text]About WebView[enabled,,]",
      "view_str": "dba62eeb47797e28f87215e5cd54fcfb"
    }
  ]
}